domainup/__init__.py
domainup/certs.py
domainup/checks.py
domainup/cli.py
domainup/config.py
domainup/docker_ops.py
domainup/local_certs.py
domainup/localhost_discovery.py
domainup/state.py
domainup/commands/add_cmd.py
domainup/commands/check_cmd.py
domainup/commands/deploy_cmd.py
domainup/commands/discover_cmd.py
domainup/commands/dns_cmd.py
domainup/commands/init_cmd.py
domainup/dns_providers/__init__.py
domainup/dns_providers/cloudflare.py
domainup/dns_providers/hetzner.py
domainup/renderers/nginx.py
domainup/renderers/traefik.py
domainup/runtime/docker-compose.yml
domainup/templates/00-redirect.conf.j2
domainup/templates/grafana.conf.j2
domainup/templates/monitoring.conf.j2
domainup/templates/nginx.conf.j2
domainup/templates/otlp.conf.j2
domainup/templates/webhooks.conf.j2
domainup/templates/nginx/00-redirect.conf.j2
domainup/templates/nginx/nginx.conf.j2
domainup/templates/nginx/nginx.conf.v02.j2
domainup/templates/nginx/vhost.conf.j2
domainup/templates/traefik/host.yml.j2
domainup/templates/traefik/traefik.yml.j2
domainup-1.0.1.dist-info/licenses/LICENSE
domainup-1.0.1.dist-info/METADATA
domainup-1.0.1.dist-info/WHEEL
domainup-1.0.1.dist-info/entry_points.txt
domainup-1.0.1.dist-info/top_level.txt
domainup-1.0.1.dist-info/RECORD
