Metadata-Version: 2.4
Name: domainup
Version: 1.0.1
Summary: Domain + HTTPS setup for Docker services (Nginx + Certbot)
Author-email: Cirrondly <contact@cirrondly.com>
License-Expression: MIT
Requires-Python: >=3.10
License-File: LICENSE
Requires-Dist: typer>=0.12
Requires-Dist: jinja2>=3.1
Requires-Dist: pyyaml>=6.0
Requires-Dist: rich>=13.7
Requires-Dist: pydantic>=2.4
Requires-Dist: requests>=2.32
Requires-Dist: docker>=7.0
Requires-Dist: questionary>=2.0
Provides-Extra: dev
Requires-Dist: pytest>=8.0; extra == "dev"
Requires-Dist: build>=1.0; extra == "dev"
Requires-Dist: twine>=6.0; extra == "dev"
Requires-Dist: ruff>=0.6; extra == "dev"
Requires-Dist: black>=24.0; extra == "dev"
Requires-Dist: mypy>=1.10; extra == "dev"
Dynamic: license-file
